blight/__init__.py
blight/_cli.py
blight/action.py
blight/constants.py
blight/enums.py
blight/exceptions.py
blight/protocols.py
blight/tool.py
blight/util.py
blight/actions/__init__.py
blight/actions/benchmark.py
blight/actions/cc_for_cxx.py
blight/actions/demo.py
blight/actions/embed_bitcode.py
blight/actions/find_inputs.py
blight/actions/find_outputs.py
blight/actions/ignore_flags.py
blight/actions/ignore_flto.py
blight/actions/ignore_werror.py
blight/actions/inject_flags.py
blight/actions/lint.py
blight/actions/record.py
blight/actions/skip_strip.py
blight-0.0.53.dist-info/entry_points.txt
blight-0.0.53.dist-info/LICENSE
blight-0.0.53.dist-info/WHEEL
blight-0.0.53.dist-info/METADATA
blight-0.0.53.dist-info/RECORD
