Metadata-Version: 2.1
Name: blight
Version: 0.0.53
Summary: A catch-all compile-tool wrapper
Author-email: William Woodruff <william@trailofbits.com>
Requires-Python: >=3.7
Classifier: Programming Language :: Python :: 3
Classifier: License :: OSI Approved :: Apache Software License
Classifier: Intended Audience :: Developers
Classifier: Topic :: Software Development :: Build Tools
Requires-Dist: click >= 7.1,< 9.0
Requires-Dist: typing_extensions
Requires-Dist: pydantic ~= 1.7
Requires-Dist: blight[doc,test] ; extra == "dev"
Requires-Dist: twine ; extra == "dev"
Requires-Dist: pdoc ; extra == "doc"
Requires-Dist: pytest ; extra == "test"
Requires-Dist: pytest-cov ; extra == "test"
Requires-Dist: pretend ; extra == "test"
Requires-Dist: coverage[toml] ; extra == "test"
Project-URL: Documentation, https://trailofbits.github.io/blight/
Project-URL: Homepage, https://pypi.org/project/blight
Project-URL: Issues, https://github.com/trailofbits/blight/issues
Project-URL: Source, https://github.com/trailofbits/blight
Provides-Extra: dev
Provides-Extra: doc
Provides-Extra: test
